deskaone_sdk_scrypt/__init__.py
deskaone_sdk_scrypt/AntiCaptcha/__init__.py
deskaone_sdk_scrypt/Client/__init__.py
deskaone_sdk_scrypt/Database/__init__.py
deskaone_sdk_scrypt/Exceptions/__init__.py
deskaone_sdk_scrypt/Internal/__init__.py
deskaone_sdk_scrypt/Internal/API.py
deskaone_sdk_scrypt/Internal/Internal.py
deskaone_sdk_scrypt/Utils/__init__.py
deskaone_sdk_scrypt/Utils/AWSRequestsAuth.py
deskaone_sdk_scrypt/Utils/Color.py
deskaone_sdk_scrypt/Utils/Crypto.py
deskaone_sdk_scrypt/Utils/ProgressBar.py
deskaone_sdk_scrypt/Utils/Reset.py
deskaone_sdk_scrypt/Utils/Timer.py
deskaone_sdk_scrypt/Utils/Typer.py
deskaone_sdk_scrypt-1.0.5.dist-info/WHEEL
deskaone_sdk_scrypt-1.0.5.dist-info/METADATA
deskaone_sdk_scrypt-1.0.5.dist-info/RECORD
